README.md
setup.py
munibot_es/__init__.py
munibot_es.egg-info/PKG-INFO
munibot_es.egg-info/SOURCES.txt
munibot_es.egg-info/dependency_links.txt
munibot_es.egg-info/entry_points.txt
munibot_es.egg-info/requires.txt
munibot_es.egg-info/top_level.txt
munibot_es/profiles/__init__.py
munibot_es/profiles/cat.py
munibot_es/profiles/es.py