Metadata-Version: 2.1
Name: munibot-es
Version: 0.0.2
Summary: A Twitter bot built with munibot that tweets aerial imagery pictures of Spain municipalities
Home-page: https://github.com/amercader/munibot_es
Author: Adrià Mercader
Author-email: amercadero@gmail.com
License: UNKNOWN
Platform: UNKNOWN
Classifier: Programming Language :: Python :: 3
Classifier: License :: OSI Approved :: MIT License
Classifier: Operating System :: OS Independent
Requires-Python: >=3.6
